{"Wash_hands": {"start": 1204291429000, "relative_end": 187000, "relative_start": 141000, "end": 1204291475000}, "Cook": {"start": 1204291494000, "relative_end": 562000, "relative_start": 206000, "end": 1204291850000}, "Phone_Call": {"start": 1204291288000, "relative_end": 117000, "relative_start": 0, "end": 1204291405000}, "Clean": {"start": 1204291985000, "relative_end": 856000, "relative_start": 697000, "end": 1204292144000}, "Eat": {"start": 1204291862000, "relative_end": 667000, "relative_start": 574000, "end": 1204291955000}}